[{"meta":{"id":"propagate","uuid":"b6d4500d-b8e4-4c91-83b5-f0c4bc2d35ae","sort":"167942000","src":"collegiate","section":"alpha","stems":["propagate","propagated","propagates","propagating","propagative","propagator","propagators"],"offensive":false},"hwi":{"hw":"prop*a*gate","prs":[{"mw":"ˈprä-pə-ˌgāt","sound":{"audio":"propag07","ref":"c","stat":"1"}}]},"fl":"verb","ins":[{"ifc":"-gat*ed","if":"prop*a*gat*ed"},{"ifc":"-gat*ing","if":"prop*a*gat*ing"}],"def":[{"vd":"transitive verb","sseq":[[["sense",{"sn":"1","dt":[["text","{bc}to cause to continue or increase by sexual or asexual reproduction"]]}]],[["sense",{"sn":"2","dt":[["text","{bc}to pass along to offspring"]]}]],[["sense",{"sn":"3 a","dt":[["text","{bc}to cause to spread out and affect a greater number or greater area {bc}{sx|extend||}"]]}],["sense",{"sn":"b","dt":[["text","{bc}to foster growing knowledge of, familiarity with, or acceptance of (something, such as an idea or belief) {bc}{sx|publicize||}"]]}],["sense",{"sn":"c","dt":[["text","{bc}to transmit (something, such as sound or light) through a medium"]]}]]]},{"vd":"intransitive verb","sseq":[[["sense",{"sn":"1","dt":[["text","{bc}to multiply sexually or asexually"]]}]],[["sense",{"sn":"2","dt":[["text","{bc}{sx|increase||}, {sx|extend||}"]]}]],[["sense",{"sn":"3","dt":[["text","{bc}to travel through space or a material "],["uns",[[["text","used of wave energy (such as light, sound, or radio waves)"]]]]]}]]]}],"uros":[{"ure":"prop*a*ga*tive","prs":[{"mw":"ˈprä-pə-ˌgā-tiv","sound":{"audio":"propag09","ref":"c","stat":"1"}}],"fl":"adjective"},{"ure":"prop*a*ga*tor","prs":[{"mw":"ˈprä-pə-ˌgā-tər","sound":{"audio":"propag10","ref":"c","stat":"1"}}],"fl":"noun"}],"et":[["text","Latin {it}propagatus{/it}, past participle of {it}propagare{/it} to set slips, propagate, from {it}propages{/it} slip, offspring, from {it}pro-{/it} before + {it}pangere{/it} to fasten {ma}{mat|pro-|}, {mat|pact|}{/ma}"]],"date":"1535{ds|t|1||}","shortdef":["to cause to continue or increase by sexual or asexual reproduction","to pass along to offspring","to cause to spread out and affect a greater number or greater area : extend"]}]