[{"meta":{"id":"zeitgeist","uuid":"918a77b5-2874-4a82-9dc0-7b5054658768","sort":"260061000","src":"collegiate","section":"alpha","stems":["zeitgeist","zeitgeists"],"offensive":false},"hwi":{"hw":"zeit*geist","prs":[{"mw":"ˈtsīt-ˌgīst","sound":{"audio":"zeitge04","ref":"c","stat":"1"}},{"mw":"ˈzīt-","sound":{"audio":"zeitge03","ref":"c","stat":"1"}}]},"fl":"noun","lbs":["often capitalized"],"def":[{"sseq":[[["sense",{"dt":[["text","{bc}the general intellectual, moral, and cultural climate of an era"]]}]]]}],"et":[["text","German, from {it}Zeit + Geist{/it} spirit"]],"date":"1835","shortdef":["the general intellectual, moral, and cultural climate of an era"]}]